README.rst
setup.py
bin/grate
sqlalchemygrate/__init__.py
sqlalchemygrate/migrations.py
sqlalchemygrate.egg-info/PKG-INFO
sqlalchemygrate.egg-info/SOURCES.txt
sqlalchemygrate.egg-info/dependency_links.txt
sqlalchemygrate.egg-info/entry_points.txt
sqlalchemygrate.egg-info/requires.txt
sqlalchemygrate.egg-info/top_level.txt