Metadata-Version: 1.0
Name: sqlalchemygrate
Version: 0.3
Summary: Silly (but effective) database schema and data migration framework using SQLAlchemy.
Home-page: http://github.com/shazow/sqlalchemygrate
Author: Andrey Petrov
Author-email: andrey.petrov@shazow.net
License: MIT
Platform: UNKNOWN
